{
    "odo": {
        "description": "ODO CLI tool",
        "vendor": "Red Hat Developer",
        "name": "odo",
        "version": "3.16.1",
        "versionRange": "^3.16.1",
        "versionRangeLabel": "version >= 3.16.1",
        "dlFileName": "odo",
        "filePrefix": "",
        "platform": {
            "win32": {
                "url": "https://s3.eu-de.cloud-object-storage.appdomain.cloud/odo-nightly-builds/odo-windows-amd64-a50a5d265.zip",
                "sha256sum": "7dc328cbd352878278b2c22ad00514dd0918462dad35254e100051fb0bf68306",
                "dlFileName": "odo-windows-amd64.zip",
                "cmdFileName": "odo-windows-amd64-a50a5d265.exe"
            },
            "darwin": {
                "url": "https://s3.eu-de.cloud-object-storage.appdomain.cloud/odo-nightly-builds/odo-darwin-amd64-a50a5d265.tar.gz",
                "sha256sum": "76f5422969b2b1087d66ed5a9b6638d2448fe1d16337e049cfc24e7b0c9fbec1",
                "dlFileName": "odo-darwin-amd64.tar.gz",
                "cmdFileName": "odo-darwin-amd64-a50a5d265"
            },
            "darwin-arm64": {
                "url": "https://s3.eu-de.cloud-object-storage.appdomain.cloud/odo-nightly-builds/odo-darwin-arm64-a50a5d265.tar.gz",
                "sha256sum": "c855525cbf439f8c71e99838a08b3d977f5eb477eef4ba52db3824b088682eee",
                "dlFileName": "odo-darwin-arm64.tar.gz",
                "cmdFileName": "odo-darwin-arm64-a50a5d265"
            },
            "linux": {
                "url": "https://s3.eu-de.cloud-object-storage.appdomain.cloud/odo-nightly-builds/odo-linux-amd64-a50a5d265.tar.gz",
                "sha256sum": "2412870f133d43bef647e24439d40955ba82d64b31ad0d3130725696f9054231",
                "dlFileName": "odo-linux-amd64.tar.gz",
                "cmdFileName": "odo-linux-amd64-a50a5d265"
            },
            "linux-arm64": {
                "url": "https://s3.eu-de.cloud-object-storage.appdomain.cloud/odo-nightly-builds/odo-linux-arm64-a50a5d265.tar.gz",
                "sha256sum": "ac6bf9669e31261abefb1746c76db16ed6e1ecb0fc347e0a58c1a12da2b291b9",
                "dlFileName": "odo-linux-arm64.tar.gz",
                "cmdFileName": "odo-linux-arm64-a50a5d265"
            }
        }
    },
    "oc": {
        "description": "OKD CLI client tool",
        "vendor": "Red Hat, Inc.",
        "name": "oc",
        "cmdFileName": "oc",
        "version": "4.18.4",
        "versionRange": "^4.18.4",
        "versionRangeLabel": "version >= 4.18.4 and < 5.0.0",
        "filePrefix": "",
        "platform": {
            "win32": {
                "url": "https://mirror.openshift.com/pub/openshift-v4/clients/ocp/4.18.4/openshift-client-windows-4.18.4.zip",
                "sha256sum": "08608b2d65750593de20dccee9cfd9c7ab22287d93e0542cfb3f54329adc9750",
                "dlFileName": "openshift-client-windows-4.18.4.zip",
                "cmdFileName": "oc.exe"
            },
            "darwin": {
                "url": "https://mirror.openshift.com/pub/openshift-v4/clients/ocp/4.18.4/openshift-client-mac-4.18.4.tar.gz",
                "sha256sum": "abe7e679ee851ff88c4f4b3e5ccd791cf26a7abfc6561ae38c886c57dcfa49ed",
                "dlFileName": "openshift-client-mac-4.18.4.tar.gz",
                "cmdFileName": "oc"
            },
            "darwin-arm64": {
                "url": "https://mirror.openshift.com/pub/openshift-v4/clients/ocp/4.18.4/openshift-client-mac-arm64-4.18.4.tar.gz",
                "sha256sum": "eb936134703e8ed55704a72f699542e84efae8899edfd41ecf3b5d28f4e29798",
                "dlFileName": "openshift-client-mac-arm64-4.18.4.tar.gz",
                "cmdFileName": "oc"
            },
            "linux": {
                "url": "https://mirror.openshift.com/pub/openshift-v4/clients/ocp/4.18.4/openshift-client-linux-4.18.4.tar.gz",
                "sha256sum": "74cdd6dca72f40f8cdd04f8d7ef1d1b8b5f3a904216d09a13fa2a03f3997d358",
                "dlFileName": "openshift-client-linux-4.18.4.tar.gz",
                "cmdFileName": "oc"
            },
            "linux-arm64": {
                "url": "https://mirror.openshift.com/pub/openshift-v4/clients/ocp/4.18.4/openshift-client-linux-arm64-4.18.4.tar.gz",
                "sha256sum": "74e932a060b481ab9c4967ef5da942a5d7c2b739a003aff1aa5dc851271dbe89",
                "dlFileName": "openshift-client-linux-arm64-4.18.4.tar.gz",
                "cmdFileName": "oc"
            }
        }
    },
    "func": {
        "description": "Function CLI tool",
        "vendor": "Red Hat, Inc.",
        "name": "func",
        "version": "1.17.0",
        "versionRange": "^1.17.0",
        "versionRangeLabel": "version >= 1.17.0",
        "dlFileName": "func",
        "cmdFileName": "func",
        "filePrefix": "",
        "platform": {
            "win32": {
                "url": "https://github.com/knative/func/releases/download/knative-v1.17.0/func_windows_amd64.exe",
                "sha256sum": "34a7e8ab4cae1981462383ef48723c65458c711e779d0b85537b7ef3076278b9",
                "dlFileName": "func_windows_amd64.exe",
                "cmdFileName": "func.exe"
            },
            "darwin": {
                "url": "https://github.com/knative/func/releases/download/knative-v1.17.0/func_darwin_amd64",
                "sha256sum": "37bbea24c0df94566b1100d9be8749417b0bf056445abe38ad73139bc8ca9dc1",
                "dlFileName": "func_darwin_amd64",
                "cmdFileName": "func"
            },
            "darwin-arm64": {
                "url": "https://github.com/knative/func/releases/download/knative-v1.17.0/func_darwin_arm64",
                "sha256sum": "7d13a65c33e60239b5b429666ff41604fe6e6ddeaa005c75b9db84e6dabfc476",
                "dlFileName": "func_darwin_arm64",
                "cmdFileName": "func"
            },
            "linux": {
                "url": "https://github.com/knative/func/releases/download/knative-v1.17.0/func_linux_amd64",
                "sha256sum": "4f0682edc5bab7bed89fb83145ab66fd2c39f420e621442aee87b21b4647a9d9",
                "dlFileName": "func_linux_amd64",
                "cmdFileName": "func"
            },
            "linux-arm64": {
                "url": "https://github.com/knative/func/releases/download/knative-v1.17.0/func_linux_arm64",
                "sha256sum": "b30e3e31c14cfde553d3209c48f5434842a382374ecbf14d6bb90c686460c45b",
                "dlFileName": "func_linux_arm64",
                "cmdFileName": "func"
            }
        }
    },
    "helm": {
        "description": "Helm CLI tool",
        "vendor": "The Helm Project",
        "name": "helm",
        "version": "3.17.2",
        "versionRange": "^3.17.2",
        "versionRangeLabel": "version >= 3.17.2",
        "dlFileName": "helm",
        "filePrefix": "",
        "platform": {
            "win32": {
                "url": "https://get.helm.sh/helm-v3.17.2-windows-amd64.zip",
                "sha256sum": "f76fe76fa116d2bae948aee9bb54ba11bf5b726a09f732ce6a74eb65af2886b1",
                "dlFileName": "helm-windows-amd64.zip",
                "cmdFileName": "helm.exe",
                "filePrefix": "windows-amd64/"
            },
            "darwin": {
                "url": "https://get.helm.sh/helm-v3.17.2-darwin-amd64.tar.gz",
                "sha256sum": "3e240238c7a3a10efd37b8e16615b28e94ba5db5957247bb42009ba6d52f76e9",
                "dlFileName": "helm-darwin-amd64.tar.gz",
                "cmdFileName": "helm",
                "filePrefix": "darwin-amd64/"
            },
            "darwin-arm64": {
                "url": "https://get.helm.sh/helm-v3.17.2-darwin-arm64.tar.gz",
                "sha256sum": "b843cebcbebc9eccb1e43aba9cca7693d32e9f2c4a35344990e3b7b381933948",
                "dlFileName": "helm-darwin-arm64.tar.gz",
                "cmdFileName": "helm",
                "filePrefix": "darwin-arm64/"
            },
            "linux": {
                "url": "https://get.helm.sh/helm-v3.17.2-linux-amd64.tar.gz",
                "sha256sum": "90c28792a1eb5fb0b50028e39ebf826531ebfcf73f599050dbd79bab2f277241",
                "dlFileName": "helm-linux-amd64.tar.gz",
                "cmdFileName": "helm",
                "filePrefix": "linux-amd64/"
            },
            "linux-arm64": {
                "url": "https://get.helm.sh/helm-v3.17.2-linux-arm64.tar.gz",
                "sha256sum": "d78d76ec7625a94991e887ac049d93f44bd70e4876200b945f813c9e1ed1df7c",
                "dlFileName": "helm-linux-arm64.tar.gz",
                "cmdFileName": "helm",
                "filePrefix": "linux-arm64/"
            }
        }
    },
    "alizer": {
        "description": "Alizer CLI tool",
        "vendor": "The Devfile Project",
        "name": "alizer",
        "version": "1.7.0",
        "versionRange": "^1.7.0",
        "versionRangeLabel": "version >= 1.7.0",
        "dlFileName": "alizer",
        "filePrefix": "",
        "platform": {
            "win32": {
                "url": "https://github.com/devfile/alizer/releases/download/v1.7.0/alizer-v1.7.0-windows-amd64.exe",
                "dlFileName": "alizer-windows-amd64.exe",
                "cmdFileName": "alizer.exe",
                "sha256sum": "a7990ab418936e6fb548df2cb01d548cf6a1673242b3137e3252b18d968cb757"
            },
            "darwin": {
                "url": "https://github.com/devfile/alizer/releases/download/v1.7.0/alizer-v1.7.0-darwin-amd64",
                "dlFileName": "alizer-darwin-amd64",
                "cmdFileName": "alizer",
                "sha256sum": "1a4f3350089b3087df4570bd8a8626bf853f23391cc30676a50a681080c956e1"
            },
            "darwin-arm64": {
                "url": "https://github.com/devfile/alizer/releases/download/v1.7.0/alizer-v1.7.0-darwin-arm64",
                "dlFileName": "alizer-darwin-arm64",
                "cmdFileName": "alizer",
                "sha256sum": "f050383e53c3462a34e69cbac8451c59536507240d8877a256e00851a4e39876"
            },
            "linux": {
                "url": "https://github.com/devfile/alizer/releases/download/v1.7.0/alizer-v1.7.0-linux-amd64",
                "dlFileName": "alizer-linux-amd64",
                "cmdFileName": "alizer",
                "sha256sum": "bf3c5fbdd465a89e54c694b8fc737facdf8d6e2243250e6b8fe3a85c262a9b89"
            },
            "linux-arm64": {
                "url": "https://github.com/devfile/alizer/releases/download/v1.7.0/alizer-v1.7.0-linux-arm64",
                "dlFileName": "alizer-linux-arm64",
                "cmdFileName": "alizer",
                "sha256sum": "182ff9279214901f0bb5a1286a7eed6c93c55a06a9fc5f0ba36758b44f7eb2df"
            }
        }
    },
    "crc": {
        "description": "crc openshift container",
        "vendor": "Red Hat, Inc.",
        "name": "crc",
        "crcVersion": "2.48.0",
        "openshiftVersion": "4.18.1"
    }
}
